niche_elf/__init__.py
niche_elf/builder.py
niche_elf/datatypes.py
niche_elf/elf.py
niche_elf/py.typed
niche_elf/structures.py
niche_elf/util.py
niche_elf-0.3.6.dist-info/licenses/LICENSE
niche_elf-0.3.6.dist-info/METADATA
niche_elf-0.3.6.dist-info/WHEEL
niche_elf-0.3.6.dist-info/top_level.txt
niche_elf-0.3.6.dist-info/RECORD
