Metadata-Version: 2.4
Name: niche-elf
Version: 0.3.6
Summary: A small library that optimizes some niche operations commonly used by debugger extensions. 
Author-email: k4lizen <k4lizen@proton.me>
License: GPLv3
Classifier: Topic :: Software Development :: Debuggers
Classifier: Topic :: Software Development :: Embedded Systems
Classifier: Topic :: System :: Operating System Kernels
Requires-Python: <4,>=3.10
License-File: LICENSE
Dynamic: license-file
